LICENSE.txt
MANIFEST.in
README.md
setup.cfg
setup.py
django_imagekit_cropper.egg-info/PKG-INFO
django_imagekit_cropper.egg-info/SOURCES.txt
django_imagekit_cropper.egg-info/dependency_links.txt
django_imagekit_cropper.egg-info/top_level.txt
imagekit_cropper/__init__.py
imagekit_cropper/fields.py
imagekit_cropper/processors.py
imagekit_cropper/registry.py
imagekit_cropper/specs.py
imagekit_cropper/utils.py
imagekit_cropper/widgets.py
imagekit_cropper/management/__init__.py
imagekit_cropper/management/commands/__init__.py
imagekit_cropper/management/commands/generateimages_cropped.py
imagekit_cropper/static/imagekit_cropper/css/imagecrop.css
imagekit_cropper/static/imagekit_cropper/jcrop/css/Jcrop.gif
imagekit_cropper/static/imagekit_cropper/jcrop/css/jquery.Jcrop.css
imagekit_cropper/static/imagekit_cropper/jcrop/css/jquery.Jcrop.min.css
imagekit_cropper/static/imagekit_cropper/jcrop/js/jquery.Jcrop.js
imagekit_cropper/static/imagekit_cropper/jcrop/js/jquery.Jcrop.min.js
imagekit_cropper/static/imagekit_cropper/jcrop/js/jquery.color.js
imagekit_cropper/static/imagekit_cropper/jcrop/js/jquery.min.js
imagekit_cropper/static/imagekit_cropper/js/imagecrop.js
imagekit_cropper/static/imagekit_cropper/js/vendor/jquery.js