Metadata-Version: 1.1
Name: django-imagekit-cropper
Version: 1.16
Summary: Allow users to manually specify image variant crops
Home-page: https://github.com/ninapavlich/django-imagekit-cropper
Author: Nina Pavlich
Author-email: nina@ninalp.com
License: MIT
Keywords: libraries,web development,cms,django,django-grappelli
Platform: UNKNOWN
Classifier: Development Status :: 4 - Beta
Classifier: Environment :: Web Environment
Classifier: Framework :: Django
Classifier: Intended Audience :: Developers
Classifier: License :: OSI Approved :: MIT License
Classifier: Natural Language :: English
Classifier: Operating System :: OS Independent
Classifier: Programming Language :: Python
